LICENSE
README.rst
aioredis_fastapi/__init__.py
aioredis_fastapi/config.py
aioredis_fastapi/methods.py
aioredis_fastapi/py.typed
aioredis_fastapi/session.py
aioredis_fastapi-1.0.1.dist-info/LICENSE
aioredis_fastapi-1.0.1.dist-info/METADATA
aioredis_fastapi-1.0.1.dist-info/WHEEL
aioredis_fastapi-1.0.1.dist-info/RECORD
