Metadata-Version: 2.1
Name: aioredis_fastapi
Version: 1.0.1
Summary: aioredis_fastapi is an asynchronous redis based session backend for FastAPI powered applications.
Home-page: https://github.com/wiseaidev/aioredis_fastapi
License: GNU General Public License v3.0
Keywords: python,aioredis,redis,fastapi
Author: Mahmoud Harmouch
Author-email: oss@wiseai.dev
Requires-Python: >=3.9
Classifier: Development Status :: 2 - Pre-Alpha
Classifier: Intended Audience :: Developers
Classifier: License :: Other/Proprietary License
Classifier: Natural Language :: English
Classifier: Programming Language :: Python :: 3
Classifier: Programming Language :: Python :: 3.9
Classifier: Programming Language :: Python :: 3.10
Classifier: Programming Language :: Python :: 3.11
Requires-Dist: aioredis (>=2.0.1,<3.0.0)
Requires-Dist: attrs (>=23.1.0,<24.0.0)
Requires-Dist: fastapi (>=0.105.0,<0.106.0)
Project-URL: Repository, https://github.com/wiseaidev/aioredis_fastapi
